[
    {
        "type": "Feature",
        "geometry": {
          "type": "Polygon",
          "coordinates": [[
            
            [107.60474643113004, -6.874363321839609],
            [107.60499004896343, -6.8744411114557655],
            [107.60502089436463, -6.8743013078139565],
            [107.60478016612487,-6.87425803524983],

            [107.60474643113004, -6.874363321839609]

        ]]
        },
        "properties": {
          "name": "Kantor Bandung POS UNPAR",
          "komplek" : "Universitas Katolik Parahyangan"
        }
      },

      {
        "type": "Feature",
        "geometry": {
          "type": "Polygon",
          "coordinates": [[

            [ 107.60486108781696, -6.8753589069297565 ],
            [ 107.60541738971021, -6.875469915409643 ],
            [ 107.60539530328269, -6.875605592405413 ],
            [ 107.60483762098771, -6.875521993453015 ],

            [ 107.60486108781696, -6.8753589069297565 ]
            
        ]]
        },
        "properties": {
          "name": "Gedung PPAG UNPAR",
          "komplek" : "Universitas Katolik Parahyangan"
        }
      },
     
      {
        "type": "Feature",
        "geometry": {
          "type": "Polygon",
          "coordinates": [[

            [ 107.6051633958082, -6.875003953708319 ],
            [ 107.60575144694103, -6.8751108508433445 ],
            [ 107.60571969770146, -6.875245157466089 ],
            [ 107.6051509721927, -6.875175263207957 ],

            [ 107.6051633958082, -6.875003953708319 ]
    
        ]]
        },
        "properties": {
          "name": "Fakultas Teknik Unpar",
          "komplek" : "Universitas Katolik Parahyangan"
        }
      },

      {
        "type": "Feature",
        "geometry": {
          "type": "Polygon",
          "coordinates": [[

            [ 107.60492458629263, -6.874689843427731 ],
            [ 107.60521286227439, -6.8747448764044226 ],
            [ 107.60506603097984, -6.8753911142420625 ],
            [ 107.60477769353388, -6.875319215375148 ],

            [ 107.60492458629263, -6.874689843427731 ]
    
        ]]
        },
        "properties": {
          "name": "Fakultas Teknologi Informasi dan Sains",
          "komplek" : "Universitas Katolik Parahyangan"
        }
      },

      {
        "type": "Feature",
        "geometry": {
          "type": "Polygon",
          "coordinates": [[

            [ 107.60522173493614, -6.874925318753131 ],
            [ 107.60552213320038, -6.874983531050893 ],
            [ 107.60548518582027, -6.875171724183899 ],
            [ 107.60518398435211, -6.8751135119092 ],

            [ 107.60522173493614, -6.874925318753131 ]
    
        ]]
        },
        "properties": {
          "name": "Pensiunpreneur Mentoring",
          "komplek" : "Universitas Katolik Parahyangan"
        }
      },

      {
        "type": "Feature",
        "geometry": {
          "type": "Polygon",
          "coordinates": [[

            [ 107.6055657890725, -6.875184625069291  ],
            [ 107.60578226098785, -6.875226652956103  ],
            [ 107.60575628435801, -6.875349871057376  ],
            [ 107.60554269873487, -6.87530975353954  ],

            [ 107.6055657890725, -6.875184625069291  ]
    
        ]]
        },
        "properties": {
          "name": "Auditorium Pusat Pembelajaran Arntz-Geise - PPAG UNPAR",
          "komplek" : "Universitas Katolik Parahyangan"
        }
      },

      {
        "type": "Feature",
        "geometry": {
          "type": "Polygon",
          "coordinates": [[

            [ 107.60624695410074, -6.875082420874505 ],
            [ 107.6067539794314,  -6.875179849172834 ],
            [ 107.60670202617172, -6.875443478585837 ],
            [ 107.60662120998998, -6.875430106082899 ],
            [ 107.60661447530816, -6.875465447696988 ],
            [ 107.60650287200957, -6.875446344122124 ],
            [ 107.60648747845114, -6.875511296273492 ],
            [ 107.60648844054855, -6.875511296273492 ],
            [ 107.60635855739933, -6.875484551271075 ],
            [ 107.60637298886034, -6.875420554294855 ],
            [ 107.60624984039295, -6.875394764466188 ],
            [ 107.60625946136695, -6.875362288383652 ],
            [ 107.60625561297735, -6.875361333204712 ],
            [ 107.60619500084104, -6.875347005520505 ],

            [ 107.60624695410074, -6.875082420874505 ]
    
        ]]
        },
        "properties": {
          "name": "Gedung 10 Fakultas Teknik Informatika dan Sains",
          "komplek" : "Universitas Katolik Parahyangan"
        }
      },

      {
        "type": "Feature",
        "geometry": {
          "type": "Polygon",
          "coordinates": [[

            [ 107.6067963117423, -6.874762435627132  ],
            [ 107.6069165739175, -6.874794911750659  ],
            [ 107.60690502874868, -6.874838850031915  ],
            [ 107.60678572867087, -6.874803508371224  ],

            [ 107.6067963117423, -6.874762435627132  ]
    
        ]]
        },
        "properties": {
          "name": "Student Parking Universitas Katolik Parahyangan",
          "komplek" : "Universitas Katolik Parahyangan"
        }
      },

      {
        "type": "Feature",
        "geometry": {
          "type": "Polygon",
          "coordinates": [[

            [ 107.60598599516547, -6.874073057045554   ],
            [ 107.60606981419045, -6.874093694738513   ],
            [ 107.60605707369864, -6.874138964513468   ],
            [ 107.60610736511363, -6.874152279152346   ],
            [ 107.60607450805585, -6.874282096861799   ],
            [ 107.60594307982467, -6.8742501417366135   ],

            [ 107.60598599516547, -6.874073057045554 ]
    
        ]]
        },
        "properties": {
          "name": "Klinik Pratama UNPAR",
          "komplek" : "Universitas Katolik Parahyangan"
        }
      },

      {
        "type": "Feature",
        "geometry": {
          "type": "Polygon",
          "coordinates": [[

            [ 107.60613169137942, -6.87409182199783  ],
            [ 107.60623932070403, -6.874119732053457 ],
            [ 107.60619193167305, -6.874311912677624 ],
            [ 107.60608269594059, -6.874284002633293 ],

            [ 107.60613169137942, -6.87409182199783 ]
    
        ]]
        },
        "properties": {
          "name": "Samoyed WhiteCrystal",
          "komplek" : "Universitas Katolik Parahyangan"
        }
      }
      
]